README.md
provision-config-sample.toml
dotbot_provision/__init__.py
dotbot_provision/cli.py
dotbot_provision/nrf_flash.py
dotbot_provision-0.1.4.dist-info/METADATA
dotbot_provision-0.1.4.dist-info/WHEEL
dotbot_provision-0.1.4.dist-info/entry_points.txt
dotbot_provision-0.1.4.dist-info/RECORD
