Metadata-Version: 2.4
Name: dotbot-provision
Version: 0.1.4
Summary: A command-line tool for provisioning DotBot devices and gateways.
Author-email: Geovane Fedrecheski <geovane.fedrecheski@inria.fr>
Classifier: Operating System :: MacOS
Classifier: Operating System :: Microsoft :: Windows
Classifier: Operating System :: POSIX :: Linux
Classifier: Programming Language :: Python :: 3
Requires-Python: >=3.8
Requires-Dist: click>=8.1.7
Requires-Dist: intelhex>=2.3.0
Requires-Dist: tomli>=2.0.1; python_version < '3.11'
